azure_eventhub_listener/__init__.py
azure_eventhub_listener/main.py
azure_eventhub_listener-0.1.6.dist-info/LICENSE
azure_eventhub_listener-0.1.6.dist-info/METADATA
azure_eventhub_listener-0.1.6.dist-info/WHEEL
azure_eventhub_listener-0.1.6.dist-info/entry_points.txt
azure_eventhub_listener-0.1.6.dist-info/RECORD
