Metadata-Version: 2.1
Name: azure-eventhub-listener
Version: 0.1.6
Summary: A listener for Azure Event Hub events.
Home-page: https://python-poetry.org/
License: MIT
Author: Sameer Chaudhari
Author-email: sameervchaudhari@gmail.com
Requires-Python: >=3.9.3,<4.0.0
Classifier: License :: OSI Approved :: MIT License
Classifier: Programming Language :: Python :: 3
Classifier: Programming Language :: Python :: 3.10
Classifier: Programming Language :: Python :: 3.11
Classifier: Programming Language :: Python :: 3.12
Requires-Dist: azure-eventhub (>=5.11.0,<6.0.0)
Requires-Dist: requests (>=2.28.1,<3.0.0)
